src/yaddd/main.py
yaddd-0.1.0.dist-info/METADATA
yaddd-0.1.0.dist-info/WHEEL
yaddd-0.1.0.dist-info/RECORD
