Metadata-Version: 2.1
Name: yaddd
Version: 0.1.0
Summary: Yet another DDD for Python
Author: Andreev, Yury
Requires-Python: ==3.12.*
Classifier: Programming Language :: Python :: 3
Classifier: Programming Language :: Python :: 3.12
